pcfile/Files.py
pcfile/__init__.py
pcfile-0.3.0.dist-info/LICENSE
pcfile-0.3.0.dist-info/METADATA
pcfile-0.3.0.dist-info/WHEEL
pcfile-0.3.0.dist-info/top_level.txt
pcfile-0.3.0.dist-info/RECORD
