Metadata-Version: 2.1
Name: pcfile
Version: 0.3.0
Summary: A package for easy navigation in computer files
Author-email: EV <example@example.com>
License: MIT License
Classifier: Programming Language :: Python :: 3
Classifier: License :: OSI Approved :: MIT License
Classifier: Operating System :: OS Independent
Requires-Python: >=3.6
License-File: LICENSE
